README.rst
setup.py
dict_digger/__init__.py
dict_digger.egg-info/PKG-INFO
dict_digger.egg-info/SOURCES.txt
dict_digger.egg-info/dependency_links.txt
dict_digger.egg-info/not-zip-safe
dict_digger.egg-info/top_level.txt