Metadata-Version: 1.0
Name: dict-digger
Version: 0.1.1
Summary: Useful syntax for digging into nested dictionaries, and removes the need to check if a key exists
Home-page: https://github.com/jtushman/dict_digger
Author: Jonathan Tushman
Author-email: jonathan@zefr.com
License: MIT
Platform: UNKNOWN
